sshtunnel_requests/__init__.py
sshtunnel_requests/_requests.py
sshtunnel_requests/cache.py
sshtunnel_requests/sessions.py
sshtunnel_requests/ssh.py
sshtunnel_requests-0.1.3.dist-info/LICENSE
sshtunnel_requests-0.1.3.dist-info/METADATA
sshtunnel_requests-0.1.3.dist-info/WHEEL
sshtunnel_requests-0.1.3.dist-info/top_level.txt
sshtunnel_requests-0.1.3.dist-info/RECORD
