Metadata-Version: 2.1
Name: sshtunnel-requests
Version: 0.1.3
Summary: a simple HTTP library to port forward requests on SSH tunnels to remove server
Home-page: https://github.com/featureoverload/sshtunnel-requests
Author: Feature Overload
Author-email: featureoverload@gmail.com
Maintainer: Feature Overload
Maintainer-email: featureoverload@gmail.com
License: UNKNOWN
Project-URL: Documentation, https://sshtunnel-requests.readthedocs.io/en/latest/
Project-URL: Source, https://github.com/featureoverload/sshtunnel-requests
Project-URL: Tracker, https://github.com/featureoverload/sshtunnel-requests/issues
Platform: UNKNOWN
Requires-Python: >=3.8
License-File: LICENSE
Requires-Dist: requests (>=2.26.0)
Requires-Dist: sshtunnel (>=0.4.0)
Requires-Dist: furl (>=2.1.3)
Provides-Extra: all
Requires-Dist: pytest (>=6.2.5) ; extra == 'all'
Requires-Dist: pytest-mock (>=3.6.1) ; extra == 'all'
Requires-Dist: sphinx ; extra == 'all'
Requires-Dist: sphinx-rtd-theme (==1.0.0) ; extra == 'all'
Requires-Dist: recommonmark (==0.7.1) ; extra == 'all'
Provides-Extra: docs
Requires-Dist: sphinx ; extra == 'docs'
Requires-Dist: sphinx-rtd-theme (==1.0.0) ; extra == 'docs'
Requires-Dist: recommonmark (==0.7.1) ; extra == 'docs'
Provides-Extra: test
Requires-Dist: pytest (>=6.2.5) ; extra == 'test'
Requires-Dist: pytest-mock (>=3.6.1) ; extra == 'test'
